livewrapped_sdk/__init__.py
livewrapped_sdk/_base_client.py
livewrapped_sdk/_client.py
livewrapped_sdk/_compat.py
livewrapped_sdk/_constants.py
livewrapped_sdk/_exceptions.py
livewrapped_sdk/_files.py
livewrapped_sdk/_models.py
livewrapped_sdk/_qs.py
livewrapped_sdk/_resource.py
livewrapped_sdk/_response.py
livewrapped_sdk/_streaming.py
livewrapped_sdk/_types.py
livewrapped_sdk/_version.py
livewrapped_sdk/py.typed
livewrapped_sdk/_utils/__init__.py
livewrapped_sdk/_utils/_logs.py
livewrapped_sdk/_utils/_proxy.py
livewrapped_sdk/_utils/_reflection.py
livewrapped_sdk/_utils/_streams.py
livewrapped_sdk/_utils/_sync.py
livewrapped_sdk/_utils/_transform.py
livewrapped_sdk/_utils/_typing.py
livewrapped_sdk/_utils/_utils.py
livewrapped_sdk/lib/.keep
livewrapped_sdk/resources/__init__.py
livewrapped_sdk/resources/account.py
livewrapped_sdk/resources/statistics_v2.py
livewrapped_sdk/resources/stats_inventory/__init__.py
livewrapped_sdk/resources/stats_inventory/account_details.py
livewrapped_sdk/resources/stats_inventory/buyers.py
livewrapped_sdk/resources/stats_inventory/stats_inventory.py
livewrapped_sdk/resources/stats_inventory/publishers/__init__.py
livewrapped_sdk/resources/stats_inventory/publishers/publishers.py
livewrapped_sdk/resources/stats_inventory/publishers/sites.py
livewrapped_sdk/resources/stats_inventory/sites/__init__.py
livewrapped_sdk/resources/stats_inventory/sites/ad_units.py
livewrapped_sdk/resources/stats_inventory/sites/sites.py
livewrapped_sdk/types/__init__.py
livewrapped_sdk/types/account_login_params.py
livewrapped_sdk/types/account_login_response.py
livewrapped_sdk/types/statistics_v2_create_params.py
livewrapped_sdk/types/stats_response.py
livewrapped_sdk/types/stats_inventory/__init__.py
livewrapped_sdk/types/stats_inventory/account_details.py
livewrapped_sdk/types/stats_inventory/buyer_minimal.py
livewrapped_sdk/types/stats_inventory/publisher_minimal.py
livewrapped_sdk/types/stats_inventory/publishers/__init__.py
livewrapped_sdk-0.0.4.dist-info/METADATA
livewrapped_sdk-0.0.4.dist-info/WHEEL
livewrapped_sdk-0.0.4.dist-info/licenses/LICENSE
livewrapped_sdk-0.0.4.dist-info/RECORD
